mozilla_aws_cli_config/__init__.py
mozilla_aws_cli_mozilla-1.3.1.dist-info/LICENSE
mozilla_aws_cli_mozilla-1.3.1.dist-info/METADATA
mozilla_aws_cli_mozilla-1.3.1.dist-info/WHEEL
mozilla_aws_cli_mozilla-1.3.1.dist-info/top_level.txt
mozilla_aws_cli_mozilla-1.3.1.dist-info/RECORD
