Metadata-Version: 2.1
Name: mozilla-aws-cli-mozilla
Version: 1.3.1
Summary: Mozilla specific deployment of the mozilla_aws_cli
Home-page: https://github.com/mozilla-iam/mozilla-aws-cli-mozilla
Author: Mozilla Enterprise Information Security
Author-email: iam@discourse.mozilla.org
License: UNKNOWN
Keywords: maws Mozilla AWS CLI config
Platform: UNKNOWN
Classifier: Development Status :: 5 - Production/Stable
Classifier: Intended Audience :: Developers
Classifier: License :: OSI Approved :: Mozilla Public License 2.0 (MPL 2.0)
Classifier: Natural Language :: English
Classifier: Programming Language :: Python :: 2
Classifier: Programming Language :: Python :: 3
License-File: LICENSE
Requires-Dist: mozilla-aws-cli (>=1.2.5)
